Cosmos/Content.py
Cosmos/Cosmos.py
Cosmos/__init__.py
Cosmos/Exceptions/NoApiKeyException.py
Cosmos/Exceptions/NoPrivateKeyException.py
Cosmos/Exceptions/NotFoundInApiException.py
Cosmos/Exceptions/__init__.py
Cosmos/Security/Encryption.py
Cosmos/Security/__init__.py
Cosmos/Storage/Cache.py
Cosmos/Storage/__init__.py
cosmos_python-1.1.0.dist-info/DESCRIPTION.rst
cosmos_python-1.1.0.dist-info/METADATA
cosmos_python-1.1.0.dist-info/RECORD
cosmos_python-1.1.0.dist-info/WHEEL
cosmos_python-1.1.0.dist-info/metadata.json
cosmos_python-1.1.0.dist-info/top_level.txt
