Metadata-Version: 2.0
Name: cosmos-python
Version: 1.1.0
Summary: The Python SDK for CosMoS, the universal cms.
Home-page: https://github.com/cosmos-cms/cosmos-python
Author: Marius Birkhoff
Author-email: mariusbirkhoff@hotmail.com
License: MIT
Keywords: cosmos universal cms
Platform: UNKNOWN
Classifier: Development Status :: 4 - Beta
Classifier: Intended Audience :: Developers
Classifier: Topic :: Software Development :: Build Tools
Classifier: License :: OSI Approved :: MIT License
Classifier: Programming Language :: Python :: 3
Classifier: Programming Language :: Python :: 3.3
Classifier: Programming Language :: Python :: 3.4
Classifier: Programming Language :: Python :: 3.5
Requires-Dist: pycryptodomex
